{
	"info": {
		"_postman_id": "06b70465-c293-4321-a014-e8ca0fff0d72",
		"name": "gate-keeper",
		"schema": "https://schema.getpostman.com/json/collection/v2.1.0/collection.json"
	},
	"item": [
		{
			"name": "http://localhost:8000/api/healthchecker",
			"request": {
				"method": "GET",
				"header": [],
				"url": {
					"raw": "http://localhost:8000/api/healthchecker",
					"protocol": "http",
					"host": [
						"localhost"
					],
					"port": "8000",
					"path": [
						"api",
						"healthchecker"
					]
				}
			},
			"response": []
		},
		{
			"name": "http://localhost:8000/api/users/me",
			"request": {
				"method": "GET",
				"header": [],
				"url": {
					"raw": "http://localhost:8000/api/users/me",
					"protocol": "http",
					"host": [
						"localhost"
					],
					"port": "8000",
					"path": [
						"api",
						"users",
						"me"
					]
				}
			},
			"response": []
		},
		{
			"name": "http://localhost:8000/api/auth/logout",
			"request": {
				"method": "GET",
				"header": [],
				"url": {
					"raw": "http://localhost:8000/api/auth/logout",
					"protocol": "http",
					"host": [
						"localhost"
					],
					"port": "8000",
					"path": [
						"api",
						"auth",
						"logout"
					]
				}
			},
			"response": []
		},
		{
			"name": "http://localhost:8000/api/auth/refresh",
			"request": {
				"method": "GET",
				"header": [],
				"url": {
					"raw": "http://localhost:8000/api/auth/refresh",
					"protocol": "http",
					"host": [
						"localhost"
					],
					"port": "8000",
					"path": [
						"api",
						"auth",
						"refresh"
					]
				}
			},
			"response": []
		},
		{
			"name": "http://localhost:8000/api/auth/register",
			"request": {
				"method": "POST",
				"header": [],
				"body": {
					"mode": "raw",
					"raw": "{\r\n    \"email\": \"da_semenov@list.ru\",\r\n    \"name\": \"Denis\",\r\n    \"surname\": \"Semenov\",\r\n    \"password\": \"qwerty123\",\r\n    \"passwordConfirm\": \"qwerty123\"\r\n}"
				},
				"url": {
					"raw": "http://localhost:8000/api/auth/register",
					"protocol": "http",
					"host": [
						"localhost"
					],
					"port": "8000",
					"path": [
						"api",
						"auth",
						"register"
					]
				}
			},
			"response": []
		},
		{
			"name": "http://localhost:8000/api/auth/login",
			"request": {
				"method": "POST",
				"header": [],
				"body": {
					"mode": "raw",
					"raw": "{\r\n    \"email\": \"da_semenov@list.ru\",\r\n    \"password\": \"qwerty123\"\r\n}"
				},
				"url": {
					"raw": "http://localhost:8000/api/auth/login",
					"protocol": "http",
					"host": [
						"localhost"
					],
					"port": "8000",
					"path": [
						"api",
						"auth",
						"login"
					]
				}
			},
			"response": []
		}
	]
}